aliyunsdkfacebody/__init__.py
aliyunsdkfacebody/endpoint.py
aliyunsdkfacebody/request/__init__.py
aliyunsdkfacebody/request/v20191230/AddFaceEntityRequest.py
aliyunsdkfacebody/request/v20191230/AddFaceImageTemplateRequest.py
aliyunsdkfacebody/request/v20191230/AddFaceRequest.py
aliyunsdkfacebody/request/v20191230/BatchAddFacesRequest.py
aliyunsdkfacebody/request/v20191230/BeautifyBodyRequest.py
aliyunsdkfacebody/request/v20191230/BlurFaceRequest.py
aliyunsdkfacebody/request/v20191230/BodyPostureRequest.py
aliyunsdkfacebody/request/v20191230/CompareFaceRequest.py
aliyunsdkfacebody/request/v20191230/CompareFaceWithMaskRequest.py
aliyunsdkfacebody/request/v20191230/CreateFaceDbRequest.py
aliyunsdkfacebody/request/v20191230/DeepfakeFaceRequest.py
aliyunsdkfacebody/request/v20191230/DeleteFaceDbRequest.py
aliyunsdkfacebody/request/v20191230/DeleteFaceEntityRequest.py
aliyunsdkfacebody/request/v20191230/DeleteFaceImageTemplateRequest.py
aliyunsdkfacebody/request/v20191230/DeleteFaceRequest.py
aliyunsdkfacebody/request/v20191230/DetectBodyCountRequest.py
aliyunsdkfacebody/request/v20191230/DetectCelebrityRequest.py
aliyunsdkfacebody/request/v20191230/DetectChefCapRequest.py
aliyunsdkfacebody/request/v20191230/DetectFaceRequest.py
aliyunsdkfacebody/request/v20191230/DetectInfraredLivingFaceRequest.py
aliyunsdkfacebody/request/v20191230/DetectLivingFaceRequest.py
aliyunsdkfacebody/request/v20191230/DetectPedestrianIntrusionRequest.py
aliyunsdkfacebody/request/v20191230/DetectPedestrianRequest.py
aliyunsdkfacebody/request/v20191230/DetectVideoLivingFaceRequest.py
aliyunsdkfacebody/request/v20191230/EnhanceFaceRequest.py
aliyunsdkfacebody/request/v20191230/ExtractFingerPrintRequest.py
aliyunsdkfacebody/request/v20191230/ExtractPedestrianFeatureAttrRequest.py
aliyunsdkfacebody/request/v20191230/FaceBeautyRequest.py
aliyunsdkfacebody/request/v20191230/FaceFilterRequest.py
aliyunsdkfacebody/request/v20191230/FaceMakeupRequest.py
aliyun_python_sdk_facebody-2.0.14.dist-info/LICENSE
aliyun_python_sdk_facebody-2.0.14.dist-info/METADATA
aliyun_python_sdk_facebody-2.0.14.dist-info/WHEEL
aliyun_python_sdk_facebody-2.0.14.dist-info/top_level.txt
aliyun_python_sdk_facebody-2.0.14.dist-info/RECORD
